docs/generate.py
molecularnodes/__init__.py
molecularnodes/color.py
molecularnodes/download.py
molecularnodes/handlers.py
molecularnodes/session.py
molecularnodes/utils.py
molecularnodes/annotations/__init__.py
molecularnodes/annotations/base.py
molecularnodes/annotations/interface.py
molecularnodes/annotations/manager.py
molecularnodes/annotations/node_tree.py
molecularnodes/annotations/props.py
molecularnodes/annotations/utils.py
molecularnodes/annotations/fonts/Inter.woff2
molecularnodes/assets/__init__.py
molecularnodes/assets/data.py
molecularnodes/assets/node_data_file.blend
molecularnodes/assets/nodes.yml
molecularnodes/assets/template.py
molecularnodes/assets/template/startup.blend
molecularnodes/blender/__init__.py
molecularnodes/blender/coll.py
molecularnodes/blender/mesh.py
molecularnodes/blender/utils.py
molecularnodes/converters/__init__.py
molecularnodes/converters/biotite.py
molecularnodes/entities/__init__.py
molecularnodes/entities/annotations.py
molecularnodes/entities/base.py
molecularnodes/entities/utilities.py
molecularnodes/entities/density/__init__.py
molecularnodes/entities/density/annotations.py
molecularnodes/entities/density/base.py
molecularnodes/entities/density/grids.py
molecularnodes/entities/density/io.py
molecularnodes/entities/ensemble/__init__.py
molecularnodes/entities/ensemble/base.py
molecularnodes/entities/ensemble/cellpack.py
molecularnodes/entities/ensemble/io.py
molecularnodes/entities/ensemble/reader.py
molecularnodes/entities/ensemble/star.py
molecularnodes/entities/molecule/__init__.py
molecularnodes/entities/molecule/annotations.py
molecularnodes/entities/molecule/assembly.py
molecularnodes/entities/molecule/base.py
molecularnodes/entities/molecule/pdb.py
molecularnodes/entities/molecule/pdbx.py
molecularnodes/entities/molecule/reader.py
molecularnodes/entities/molecule/sdf.py
molecularnodes/entities/molecule/selections.py
molecularnodes/entities/trajectory/__init__.py
molecularnodes/entities/trajectory/annotations.py
molecularnodes-4.5.5.dist-info/licenses/LICENSE
molecularnodes-4.5.5.dist-info/licenses/LICENSE.OLD
molecularnodes-4.5.5.dist-info/METADATA
molecularnodes-4.5.5.dist-info/WHEEL
molecularnodes-4.5.5.dist-info/top_level.txt
molecularnodes-4.5.5.dist-info/RECORD
