Metadata-Version: 2.4
Name: molecularnodes
Version: 4.5.5
Summary: Toolbox for molecular animations with Blender and Geometry Nodes.
Maintainer-email: Brady Johnston <brady.johnston@me.com>
Project-URL: Homepage, https://bradyajohnston.github.io/MolecularNodes
Project-URL: Repository, https://github.com/bradyajohnston/MolecularNodes
Project-URL: Documentation, https://bradyajohnston.github.io/MolecularNodes
Requires-Python: ~=3.11.0
License-File: LICENSE
License-File: LICENSE.OLD
Requires-Dist: databpy>=0.5.1
Requires-Dist: MDAnalysis>=2.7.0
Requires-Dist: biotite>=1.5
Requires-Dist: mrcfile
Requires-Dist: starfile
Requires-Dist: PyYAML
Provides-Extra: bpy
Requires-Dist: bpy>=4.5.2; extra == "bpy"
Provides-Extra: jupyter
Requires-Dist: jupyter; extra == "jupyter"
Requires-Dist: IPython; extra == "jupyter"
Provides-Extra: build
Requires-Dist: tomlkit; extra == "build"
Provides-Extra: dev
Requires-Dist: pytest; extra == "dev"
Requires-Dist: pytest-cov; extra == "dev"
Requires-Dist: syrupy; extra == "dev"
Requires-Dist: scipy; extra == "dev"
Requires-Dist: fake-bpy-module; extra == "dev"
Requires-Dist: IPython; extra == "dev"
Requires-Dist: nodepad>=0.2.0; extra == "dev"
Provides-Extra: test
Requires-Dist: pytest; extra == "test"
Requires-Dist: pytest-cov; extra == "test"
Requires-Dist: syrupy; extra == "test"
Requires-Dist: scipy; extra == "test"
Requires-Dist: IPython; extra == "test"
Requires-Dist: pytest-xdist; extra == "test"
Requires-Dist: MDAnalysisTests>=2.7.0; extra == "test"
Requires-Dist: MDAnalysisData; extra == "test"
Requires-Dist: pooch>=1.8; extra == "test"
Requires-Dist: rdkit; extra == "test"
Requires-Dist: numpy<2.0; extra == "test"
Provides-Extra: docs
Requires-Dist: quartodoc; extra == "docs"
Requires-Dist: quarto-cli~=1.7.0; extra == "docs"
Requires-Dist: tomlkit; extra == "docs"
Requires-Dist: nodepad; extra == "docs"
Requires-Dist: jupyter; extra == "docs"
Requires-Dist: IPython; extra == "docs"
Requires-Dist: jupyter-cache; extra == "docs"
Requires-Dist: MDAnalysisTests>=2.7.0; extra == "docs"
Requires-Dist: MDAnalysisData; extra == "docs"
Dynamic: license-file
